{
  "animateLoading": true,
  "borderRadius": "{{appsmith.theme.borderRadius.appBorderRadius}}",
  "bottomRow": 5,
  "dynamicBindingPathList": [
    {
      "key": "truncateButtonColor"
    },
    {
      "key": "fontFamily"
    },
    {
      "key": "borderRadius"
    }
  ],
  "dynamicHeight": "FIXED",
  "dynamicTriggerPathList": [],
  "fontFamily": "{{appsmith.theme.fontFamily.appFont}}",
  "fontSize": "1rem",
  "fontStyle": "BOLD",
  "isLoading": false,
  "isVisible": true,
  "key": "plbjdv6jm8",
  "leftColumn": 2,
  "maxDynamicHeight": 9000,
  "minDynamicHeight": 4,
  "minWidth": 450,
  "mobileBottomRow": 6,
  "mobileLeftColumn": 22,
  "mobileRightColumn": 38,
  "mobileTopRow": 2,
  "needsErrorInfo": false,
  "overflow": "NONE",
  "parentColumnSpace": 3.05078125,
  "parentId": "ebo3o3awk6",
  "parentRowSpace": 10,
  "renderMode": "CANVAS",
  "responsiveBehavior": "fill",
  "rightColumn": 61,
  "shouldTruncate": false,
  "text": "จำนวนครั้งการโอนเงินประจำวัน",
  "textAlign": "LEFT",
  "textColor": "#231F20",
  "topRow": 1,
  "truncateButtonColor": "{{appsmith.theme.colors.primaryColor}}",
  "type": "TEXT_WIDGET",
  "version": 1,
  "widgetId": "u2ftr7haa5",
  "widgetName": "Text3Copy2"
}